{
  "title": "med",
  "carriers": [
    {
      "title": "UPS",
      "regions": [
        {
          "title": "Canada",
          "cost": "10",
          "perKg": "5"
        },
        {
          "title": "USA",
          "cost": "10",
          "perKg": "1"
        },
        {
          "title": "Rest of World",
          "cost": "4",
          "perKg": "1"
        }
      ]
    },
    {
      "title": "FEDEX",
      "regions": [
        {
          "title": "Canada",
          "cost": "10",
          "perKg": "1"
        },
        {
          "title": "USA",
          "cost": "15",
          "perKg": "-2"
        },
        {
          "title": "Rest of World",
          "cost": "27",
          "perKg": "1"
        }
      ]
    },
    {
      "title": "Canada Post",
      "regions": [
        {
          "title": "Canada",
          "cost": "8",
          "perKg": "1"
        }
      ]
    }
  ]
}